_dotdot.py
dot.py
dotdot.py
dotdotdot.py
dotdotdotdot.py
dotdot-1.1.0.dist-info/LICENSE.txt
dotdot-1.1.0.dist-info/METADATA
dotdot-1.1.0.dist-info/WHEEL
dotdot-1.1.0.dist-info/top_level.txt
dotdot-1.1.0.dist-info/zip-safe
dotdot-1.1.0.dist-info/RECORD
