Metadata-Version: 2.1
Name: dotdot
Version: 1.1.0
Summary: Make it easy to import the modules in parent directories
Home-page: https://github.com/Gsllchb/DotDot
Author: Gsllchb
Author-email: gsllchb@qq.com
License: MIT
Platform: UNKNOWN
